bandcamp_dl-0.4.dist-info/top_level.txt
bandcamp_dl-0.4.dist-info/METADATA
bandcamp_dl-0.4.dist-info/RECORD
bandcamp_dl-0.4.dist-info/DESCRIPTION.rst
bandcamp_dl-0.4.dist-info/WHEEL
bandcamp_dl-0.4.dist-info/metadata.json
bandcamp_dl/bandcampDownloader.py
bandcamp_dl/__init__.py
